zyte/__init__.py
zyte/spmstats.py
zyte_spmstats-1.0.0.dist-info/LICENSE
zyte_spmstats-1.0.0.dist-info/METADATA
zyte_spmstats-1.0.0.dist-info/WHEEL
zyte_spmstats-1.0.0.dist-info/top_level.txt
zyte_spmstats-1.0.0.dist-info/RECORD
