Metadata-Version: 2.1
Name: zyte-spmstats
Version: 1.0.0
Summary: A simple python module for Zyte's Smart Proxy Manager Stats API.
Home-page: https://github.com/mukthy/zyte-spmstats
Author: Mukthy
Author-email: muktheeswaran.m@gmail.com
Project-URL: Bug Tracker, https://github.com/mukthy/zyte-spmstats/issues
Classifier: Programming Language :: Python :: 3
Classifier: License :: OSI Approved :: MIT License
Classifier: Operating System :: OS Independent
Requires-Python: >=3.6
License-File: LICENSE
